related/__init__.py
related/_init_fields.py
related/converters.py
related/decorators.py
related/dispatchers.py
related/fields.py
related/functions.py
related/types.py
related/validators.py
related_mltoolbox-1.1.0.dist-info/WHEEL
related_mltoolbox-1.1.0.dist-info/LICENSE
related_mltoolbox-1.1.0.dist-info/METADATA
related_mltoolbox-1.1.0.dist-info/RECORD
