Metadata-Version: 2.1
Name: related-mltoolbox
Version: 1.1.0
Summary: (Fork from related) Related: Straightforward nested object models in Python
Home-page: https://git.openlogisticsfoundation.org/silicon-economy/base/ml-toolbox/related-mltoolbox
License: MIT
Keywords: related,object,models,yaml,json,dict,nested
Author: Maximilian Otten
Author-email: maximilian.otten@iml.fraunhofer.de
Requires-Python: >=3.6.2,<4.0.0
Classifier: Development Status :: 5 - Production/Stable
Classifier: Intended Audience :: Developers
Classifier: License :: OSI Approved :: MIT License
Classifier: Natural Language :: English
Classifier: Programming Language :: Python :: 3
Classifier: Programming Language :: Python :: 3.7
Classifier: Programming Language :: Python :: 3.8
Classifier: Programming Language :: Python :: 3.9
Classifier: Programming Language :: Python :: 3.10
Classifier: Programming Language :: Python :: 3.11
Requires-Dist: PyYAML
Requires-Dist: attrs
Requires-Dist: future
Requires-Dist: python-dateutil
Project-URL: Documentation, https://git.openlogisticsfoundation.org/silicon-economy/base/ml-toolbox/related-mltoolbox/-/blob/main/README.md
Project-URL: Repository, https://git.openlogisticsfoundation.org/silicon-economy/base/ml-toolbox/related-mltoolbox
